MANIFEST.in
README.rst
setup.py
gsExport/__init__.py
gsExport/exporter.py
gsExport/headings.py
gsExport/preprocessor.py
gsExport/test.tplx
gsExport/utils.py
gsExport.egg-info/PKG-INFO
gsExport.egg-info/SOURCES.txt
gsExport.egg-info/dependency_links.txt
gsExport.egg-info/requires.txt
gsExport.egg-info/top_level.txt